pdb2pqr/AUTHORS
pdb2pqr/COPYING
pdb2pqr/NEWS
pdb2pqr/README.md
pdb2pqr/__init__.py
pdb2pqr/main.py
pdb2pqr/dat/AA.xml
pdb2pqr/dat/AMBER.DAT
pdb2pqr/dat/AMBER.names
pdb2pqr/dat/CHARMM.DAT
pdb2pqr/dat/CHARMM.names
pdb2pqr/dat/HYDROGENS.xml
pdb2pqr/dat/NA.xml
pdb2pqr/dat/PARSE.DAT
pdb2pqr/dat/PARSE.names
pdb2pqr/dat/PATCHES.xml
pdb2pqr/dat/PEOEPB.DAT
pdb2pqr/dat/PEOEPB.names
pdb2pqr/dat/SWANSON.DAT
pdb2pqr/dat/SWANSON.names
pdb2pqr/dat/TOPOLOGY.xml
pdb2pqr/dat/TYL06.DAT
pdb2pqr/dat/TYL06.names
pdb2pqr/extensions/__init__.py
pdb2pqr/extensions/chi.py
pdb2pqr/extensions/contact.py
pdb2pqr/extensions/hbond.py
pdb2pqr/extensions/newresinter.py
pdb2pqr/extensions/rama.py
pdb2pqr/extensions/resinter.py
pdb2pqr/extensions/salt.py
pdb2pqr/extensions/summary.py
pdb2pqr/propka30/__init__.py
pdb2pqr/propka30/compare.py
pdb2pqr/propka30/experiment.py
pdb2pqr/propka30/propka.py
pdb2pqr/propka30/propka_det.py
pdb2pqr/propka30/propka_gui.py
pdb2pqr/propka30/propka_mut.py
pdb2pqr/propka30/propka_pdb.py
pdb2pqr/propka30/Source/__init__.py
pdb2pqr/propka30/Source/bonds.py
pdb2pqr/propka30/Source/calculator.py
pdb2pqr/propka30/Source/chain.py
pdb2pqr/propka30/Source/compare.py
pdb2pqr/propka30/Source/corresponding_atoms.py
pdb2pqr/propka30/Source/coupled_residues.py
pdb2pqr/propka30/Source/debug.py
pdb2pqr/propka30/Source/determinant.py
pdb2pqr/propka30/Source/determinants.py
pdb2pqr/propka30/Source/ions.list
pdb2pqr/propka30/Source/iterative.py
pdb2pqr/propka30/Source/lib.py
pdb2pqr/propka30/Source/ligand.py
pdb2pqr/propka30/Source/mutate.py
pdb2pqr/propka30/Source/output.py
pdb2pqr/propka30/Source/parameters.py
pdb2pqr/propka30/Source/parameters_new.py
pdb2pqr/propka30/Source/parameters_std.py
pdb2pqr/propka30/Source/pdb.py
pdb2pqr/propka30/Source/protein.py
pdb2pqr/propka30/Source/protein_bonds.dat
pdb2pqr/propka30/Source/protonate.py
pdb2pqr/propka30/Source/protonator.py
pdb2pqr/propka30/Source/residue.py
pdb2pqr/propka30/Source/rotate.py
pdb2pqr/propka30/Source/vector_algebra.py
pdb2pqr_htmd_propka30-0.0.4.dist-info/METADATA
pdb2pqr_htmd_propka30-0.0.4.dist-info/WHEEL
pdb2pqr_htmd_propka30-0.0.4.dist-info/entry_points.txt
pdb2pqr_htmd_propka30-0.0.4.dist-info/top_level.txt
pdb2pqr_htmd_propka30-0.0.4.dist-info/RECORD
