Metadata-Version: 2.1
Name: pdb2pqr-htmd-propka30
Version: 0.0.4
Summary: PDB2PQR: an automated pipeline for the setup of Poisson-Boltzmann electrostatics calculations
Home-page: http://www.poissonboltzmann.org/
License: BSD
Platform: UNKNOWN
Classifier: Development Status :: 5 - Production/Stable
Classifier: License :: OSI Approved :: GNU General Public License v2 (GPLv2)
Classifier: Natural Language :: English
Classifier: Operating System :: OS Independent
Classifier: Programming Language :: Python :: 3
Classifier: Programming Language :: Python :: 3.8
Classifier: Programming Language :: Python :: 3.7
Classifier: Programming Language :: Python :: 3.6
Classifier: Programming Language :: Python :: 3.5
Classifier: Topic :: Scientific/Engineering :: Bio-Informatics
